{"title":"어피티 ─ 뉴스","url":"https://uppity.co.kr/news","favicon":"https://cdn.imweb.me/thumbnail/20210325/af054619b1784.png","elements":[{"title":"[2023. 06. 29] 임금을 후불제로 올려요?","contents":"산업","link":"https://uppity.co.kr/news/?q=YToxOntzOjEyOiJrZXl3b3JkX3R5cGUiO3M6MzoiYWxsIjt9&bmode=view&idx=15559704&t=board","retrieved":1688009394433},{"title":"[2023. 06. 29] 일본, ‘화이트리스트’ 재지정","contents":"글로벌","link":"https://uppity.co.kr/news/?q=YToxOntzOjEyOiJrZXl3b3JkX3R5cGUiO3M6MzoiYWxsIjt9&bmode=view&idx=15559697&t=board","retrieved":1688009394434},{"title":"[2023. 06. 28] 리볼빙, 멈춰!","contents":"생활경제","link":"https://uppity.co.kr/news/?q=YToxOntzOjEyOiJrZXl3b3JkX3R5cGUiO3M6MzoiYWxsIjt9&bmode=view&idx=15549693&t=board","retrieved":1687907913177},{"title":"[2023. 06. 28] 위탁생산 3형제, 알고 갑시다","contents":"산업","link":"https://uppity.co.kr/news/?q=YToxOntzOjEyOiJrZXl3b3JkX3R5cGUiO3M6MzoiYWxsIjt9&bmode=view&idx=15549689&t=board","retrieved":1687907913178},{"title":"[2023. 06. 27] 현대건설의 대규모 수주","contents":"산업","link":"https://uppity.co.kr/news/?q=YToxOntzOjEyOiJrZXl3b3JkX3R5cGUiO3M6MzoiYWxsIjt9&bmode=view&idx=15542307&t=board","retrieved":1687836799621},{"title":"[2023. 06. 27] 합법 대출인데 불법이다?","contents":"생활경제","link":"https://uppity.co.kr/news/?q=YToxOntzOjEyOiJrZXl3b3JkX3R5cGUiO3M6MzoiYWxsIjt9&bmode=view&idx=15542252&t=board","retrieved":1687836799627},{"title":"[2023. 06. 26] 상장 당일, 더 뜨거워진다","contents":"증권","link":"https://uppity.co.kr/news/?q=YToxOntzOjEyOiJrZXl3b3JkX3R5cGUiO3M6MzoiYWxsIjt9&bmode=view&idx=15529620&t=board","retrieved":1687744223457},{"title":"[2023. 06. 26] 러시아발, 새로운 리스크","contents":"글로벌","link":"https://uppity.co.kr/news/?q=YToxOntzOjEyOiJrZXl3b3JkX3R5cGUiO3M6MzoiYWxsIjt9&bmode=view&idx=15529599&t=board","retrieved":1687744223458},{"title":"[2023. 06. 23] 전기자전거, 관건은 무엇?","contents":"산업","link":"https://uppity.co.kr/news/?q=YToxOntzOjEyOiJrZXl3b3JkX3R5cGUiO3M6MzoiYWxsIjt9&bmode=view&idx=15511350&t=board","retrieved":1687484794235},{"title":"[2023. 06. 23] CJ는 CGV를 구출하고 싶어","contents":"증권","link":"https://uppity.co.kr/news/?q=YToxOntzOjEyOiJrZXl3b3JkX3R5cGUiO3M6MzoiYWxsIjt9&bmode=view&idx=15511328&t=board","retrieved":1687484794236}]}