{"title":"어피티 ─ 뉴스","url":"https://uppity.co.kr/news","favicon":"https://cdn.imweb.me/thumbnail/20210325/af054619b1784.png","elements":[{"title":"[24.02.29] 10년 만에 절반으로 줄어든 출생아 수","contents":"생활경제","link":"https://uppity.co.kr/news/?q=YToxOntzOjEyOiJrZXl3b3JkX3R5cGUiO3M6MzoiYWxsIjt9&bmode=view&idx=18236024&t=board","retrieved":1709320426120},{"title":"[24.02.29] 대기업 부족이 문제의 원인이다?","contents":"경제일반","link":"https://uppity.co.kr/news/?q=YToxOntzOjEyOiJrZXl3b3JkX3R5cGUiO3M6MzoiYWxsIjt9&bmode=view&idx=18235982&t=board","retrieved":1709320426121},{"title":"[24.02.28] 밥솥 없어도 밥 잘 먹어요?","contents":"산업","link":"https://uppity.co.kr/news/?q=YToxOntzOjEyOiJrZXl3b3JkX3R5cGUiO3M6MzoiYWxsIjt9&bmode=view&idx=18218121&t=board","retrieved":1709320426130},{"title":"[24.02.28] 외국인에게 더 비싼 이중가격제","contents":"글로벌","link":"https://uppity.co.kr/news/?q=YToxOntzOjEyOiJrZXl3b3JkX3R5cGUiO3M6MzoiYWxsIjt9&bmode=view&idx=18218105&t=board","retrieved":1709320426132},{"title":"[24.02.27] 내가 알 만한 기업의 상장이라?","contents":"증권","link":"https://uppity.co.kr/news/?q=YToxOntzOjEyOiJrZXl3b3JkX3R5cGUiO3M6MzoiYWxsIjt9&bmode=view&idx=18203385&t=board","retrieved":1709320426135},{"title":"[24.02.27] 시장의 새로운 빅이슈: AI와 중국","contents":"금융","link":"https://uppity.co.kr/news/?q=YToxOntzOjEyOiJrZXl3b3JkX3R5cGUiO3M6MzoiYWxsIjt9&bmode=view&idx=18203359&t=board","retrieved":1709320426136},{"title":"[24.02.26] 대출한도 전만큼 잘 안 나온다?","contents":"생활경제","link":"https://uppity.co.kr/news/?q=YToxOntzOjEyOiJrZXl3b3JkX3R5cGUiO3M6MzoiYWxsIjt9&bmode=view&idx=18177656&t=board","retrieved":1709320426138},{"title":"[24.02.26] 은행 없는 금융회사들, 이렇게 잘나가도 되나요","contents":"금융","link":"https://uppity.co.kr/news/?q=YToxOntzOjEyOiJrZXl3b3JkX3R5cGUiO3M6MzoiYWxsIjt9&bmode=view&idx=18177591&t=board","retrieved":1709320426139},{"title":"[24.02.23] 조금 더 자세한 정부-의료계 쟁점 정리.zip","contents":"경제정책","link":"https://uppity.co.kr/news/?q=YToxOntzOjEyOiJrZXl3b3JkX3R5cGUiO3M6MzoiYWxsIjt9&bmode=view&idx=18154634&t=board","retrieved":1709320426141},{"title":"[24.02.23] 엔비디아, 분기 29조 매출","contents":"산업","link":"https://uppity.co.kr/news/?q=YToxOntzOjEyOiJrZXl3b3JkX3R5cGUiO3M6MzoiYWxsIjt9&bmode=view&idx=18154619&t=board","retrieved":1709320426142}]}