{"title":"어피티 ─ 뉴스","url":"https://uppity.co.kr/news","favicon":"https://cdn.imweb.me/thumbnail/20210325/af054619b1784.png","elements":[{"title":"[23.09.04] SEC: 아직은 좀 이른걸?","contents":"증권","link":"https://uppity.co.kr/news/?q=YToxOntzOjEyOiJrZXl3b3JkX3R5cGUiO3M6MzoiYWxsIjt9&bmode=view&idx=16224167&t=board","retrieved":1693782924787},{"title":"[23.09.04] 티빙을 제친 쿠팡플레이","contents":"경제일반","link":"https://uppity.co.kr/news/?q=YToxOntzOjEyOiJrZXl3b3JkX3R5cGUiO3M6MzoiYWxsIjt9&bmode=view&idx=16224163&t=board","retrieved":1693782924790},{"title":"[23.09.01] 한국 경제 성적표는 또 왜 이래?","contents":"경제일반","link":"https://uppity.co.kr/news/?q=YToxOntzOjEyOiJrZXl3b3JkX3R5cGUiO3M6MzoiYWxsIjt9&bmode=view&idx=16201721&t=board","retrieved":1693530713838},{"title":"[23.09.01] 나빠졌다니, 오히려 좋아?","contents":"글로벌","link":"https://uppity.co.kr/news/?q=YToxOntzOjEyOiJrZXl3b3JkX3R5cGUiO3M6MzoiYWxsIjt9&bmode=view&idx=16201712&t=board","retrieved":1693530713848},{"title":"[23.08.31] 현금 없는 사회, 미국은?","contents":"금융","link":"https://uppity.co.kr/news/?q=YToxOntzOjEyOiJrZXl3b3JkX3R5cGUiO3M6MzoiYWxsIjt9&bmode=view&idx=16193094&t=board","retrieved":1693455537692},{"title":"[23.08.31] 질러야 경제가 삽니다","contents":"글로벌","link":"https://uppity.co.kr/news/?q=YToxOntzOjEyOiJrZXl3b3JkX3R5cGUiO3M6MzoiYWxsIjt9&bmode=view&idx=16193075&t=board","retrieved":1693455537694},{"title":"[23.08.30] 중립금리? 중립적인 금리?","contents":"글로벌","link":"https://uppity.co.kr/news/?q=YToxOntzOjEyOiJrZXl3b3JkX3R5cGUiO3M6MzoiYWxsIjt9&bmode=view&idx=16180219&t=board","retrieved":1693357595121},{"title":"[23.08.30] 2024년 정부의 예산은?","contents":"경제정책","link":"https://uppity.co.kr/news/?q=YToxOntzOjEyOiJrZXl3b3JkX3R5cGUiO3M6MzoiYWxsIjt9&bmode=view&idx=16180203&t=board","retrieved":1693357595121},{"title":"[23.08.29] 탑승 전, 체중계에 오르는 이유","contents":"생활경제","link":"https://uppity.co.kr/news/?q=YToxOntzOjEyOiJrZXl3b3JkX3R5cGUiO3M6MzoiYWxsIjt9&bmode=view&idx=16173313&t=board","retrieved":1693293286308},{"title":"[23.08.29] 핵 오염수 방류,  국제 사회의 반응은?","contents":"글로벌","link":"https://uppity.co.kr/news/?q=YToxOntzOjEyOiJrZXl3b3JkX3R5cGUiO3M6MzoiYWxsIjt9&bmode=view&idx=16173274&t=board","retrieved":1693293286311}]}